es_app_search/__init__.py
es_app_search/es_app_search.py
es_app_search-1.0.2.dist-info/LICENSE.md
es_app_search-1.0.2.dist-info/METADATA
es_app_search-1.0.2.dist-info/WHEEL
es_app_search-1.0.2.dist-info/top_level.txt
es_app_search-1.0.2.dist-info/RECORD
